#set( $symbol_pound = '#' )
#set( $symbol_dollar = '$' )
#set( $symbol_escape = '\' )
<ui:UiBinder xmlns:ui='urn:ui:com.google.gwt.uibinder'
             xmlns:g='urn:import:com.google.gwt.user.client.ui'>
    <ui:style>
        .widget {
            padding-bottom: 15px;    
        }
        
        .inline {
            display: inline;
        }
    </ui:style>
    
    <g:HTMLPanel styleName="{style.widget}">
        Header: 
        <a href="${symbol_pound}home">Home</a>
        <a href="${symbol_pound}admin">Admin</a>
        <g:SimplePanel ui:field="login" styleName="{style.inline}"/> 
        <g:Button ui:field="test">Test</g:Button>
    </g:HTMLPanel>
</ui:UiBinder>
